{
	"id": 7945,
	"active": true,
	"admin_emails": [],
	"alternate_name": null,
	"coordinates": [-80.2481509,
	25.90428],
	"description": "See listed services",
	"latitude": 25.90428,
	"longitude": -80.2481509,
	"name": "Opa Locka, FL",
	"short_desc": null,
	"slug": "opa-locka-fl-195121ae-cb86-46d2-a3fa-c232e692b9d0",
	"website": null,
	"updated_at": "2017-01-09T10:15:05.860-08:00",
	"url": "https://miamiopen211-api.herokuapp.com/api/locations/opa-locka-fl-195121ae-cb86-46d2-a3fa-c232e692b9d0",
	"address": {
		"id": 3865,
		"address_1": "600 Ahmad Street",
		"address_2": null,
		"city": "Opa Locka",
		"state_province": "FL",
		"postal_code": "33054"
	},
	"organization": {
		"id": 2508,
		"accreditations": [],
		"alternate_name": "STARS",
		"date_incorporated": null,
		"description": "STARS program serves 8 after school sites in Miami-Dade. The program is designed to promote positive growth and development in elementary school children through tutoring the arts and social enrichment. It also offers parent and children refuge from the troubles of out-of-school hours-boredom and danger. It incorporates tutoring in reading, sports (basketball, soccer, flag football, and volleyball). Recreational activities (dance and painting) and culturally enriching field trips (Discovery Museum, Zoo Miami, Jungle Island, Children's Museum and Miami Seaquarium).",
		"email": null,
		"funding_sources": [],
		"licenses": [],
		"name": "FCAA - SUCCESS THROUGH ARTS, READING AND SOCIALIZATION",
		"website": "http://www.fcaafamily.org",
		"slug": "fcaa-success-through-arts-reading-and-socialization",
		"url": "https://miamiopen211-api.herokuapp.com/api/organizations/fcaa-success-through-arts-reading-and-socialization",
		"locations_url": "https://miamiopen211-api.herokuapp.com/api/organizations/fcaa-success-through-arts-reading-and-socialization/locations"
	},
	"phones": [{
		"id": 7945,
		"department": null,
		"extension": null,
		"number": "305-685-4881",
		"number_type": "voice",
		"vanity_number": null
	}]
}