{
	"id": 5981,
	"active": true,
	"admin_emails": [],
	"alternate_name": null,
	"coordinates": [-80.2267854,
	25.7436678],
	"description": "See listed services",
	"latitude": 25.7436678,
	"longitude": -80.2267854,
	"name": "Miami, FL",
	"short_desc": null,
	"slug": "miami-fl-2000-south-dixie-highway",
	"website": null,
	"updated_at": "2017-01-09T10:15:05.860-08:00",
	"url": "https://miamiopen211-api.herokuapp.com/api/locations/miami-fl-2000-south-dixie-highway",
	"address": {
		"id": 2544,
		"address_1": "2000 South Dixie Highway",
		"address_2": "Suite 104",
		"city": "Miami",
		"state_province": "FL",
		"postal_code": "33133"
	},
	"organization": {
		"id": 5981,
		"accreditations": [],
		"alternate_name": null,
		"date_incorporated": null,
		"description": "A full service group with many on staff specializing in addictions. Other specialties are anxiety disorders, marriage and family therapy, brain psychotherapy, adult psychiatry, anger management, decision making, depression, divorce, grief and loss, trauma, court/divorce issues, art therapy and therapy for children provided.\n\n*Does not provide emergency care or crisis services.*",
		"email": null,
		"funding_sources": [],
		"licenses": [],
		"name": "COCONUT GROVE CENTER FOR COUNSELING, INC.",
		"website": "http://www.coconutgrovecenter.com/18701.html",
		"slug": "coconut-grove-center-for-counseling-inc",
		"url": "https://miamiopen211-api.herokuapp.com/api/organizations/coconut-grove-center-for-counseling-inc",
		"locations_url": "https://miamiopen211-api.herokuapp.com/api/organizations/coconut-grove-center-for-counseling-inc/locations"
	},
	"phones": [{
		"id": 5981,
		"department": null,
		"extension": null,
		"number": "305-446-6700",
		"number_type": "voice",
		"vanity_number": null
	}]
}