{
	"id": 1096,
	"accreditations": [],
	"alternate_name": null,
	"date_incorporated": null,
	"description": "Provides individualized vocational rehabilitation services for people with disabilities to develop the confidence, self esteem, skills and habits to enable them to become competitively employed, pursue other goals and become more self-reliant and independent. Programs include Vocational Evaluation, Work Activities, Vocational Training, Extended Training, Supported Employment, Job Development and Placement.",
	"email": null,
	"funding_sources": [],
	"licenses": [],
	"name": "GOODWILL INDUSTRIES OF SOUTH FLORIDA, INC.",
	"website": "http:\/\/www.goodwillsouthflorida.org",
	"slug": "goodwill-industries-of-south-florida-inc",
	"url": "https:\/\/miamiopen211-api.herokuapp.com\/api\/organizations\/goodwill-industries-of-south-florida-inc",
	"locations_url": "https:\/\/miamiopen211-api.herokuapp.com\/api\/organizations\/goodwill-industries-of-south-florida-inc\/locations",
	"contacts": [{
		"department": null,
		"email": "bpallango@goodwillmiami.org",
		"id": 1096,
		"name": "Bridget Pallango",
		"title": "Senior Vice President, Human Services",
		"phones": [{
			"id": 1096,
			"department": null,
			"extension": null,
			"number": "305-325-9114",
			"number_type": "voice",
			"vanity_number": null
		}]
	},
	{
		"department": null,
		"email": "questions@goodwillsouthflorida.org",
		"id": 1097,
		"name": "Robert Randall",
		"title": "Vice President, Donated Goods",
		"phones": [{
			"id": 1097,
			"department": null,
			"extension": null,
			"number": "305-325-9114",
			"number_type": "voice",
			"vanity_number": null
		}]
	},
	{
		"department": null,
		"email": "sriorda@goodwillmiami.org",
		"id": 1098,
		"name": "Silvia Riorda",
		"title": "Director of Vocational Programs",
		"phones": [{
			"id": 1098,
			"department": null,
			"extension": null,
			"number": "305-325-9114",
			"number_type": "voice",
			"vanity_number": null
		}]
	},
	{
		"department": null,
		"email": "emartinez@goodwillmiami.org",
		"id": 1099,
		"name": "Evelyn Martinez",
		"title": "Vocational Evaluation Manager",
		"phones": [{
			"id": 1099,
			"department": null,
			"extension": null,
			"number": "305-326-4166",
			"number_type": "voice",
			"vanity_number": null
		}]
	},
	{
		"department": null,
		"email": "rridgeway@goodwillmiami.org",
		"id": 1100,
		"name": "Roxana Ridgeway",
		"title": "Job Development and Placement Manager",
		"phones": [{
			"id": 1100,
			"department": null,
			"extension": null,
			"number": "305-326-4205",
			"number_type": "voice",
			"vanity_number": null
		}]
	},
	{
		"department": null,
		"email": "sriorda@goodwillmiami.org",
		"id": 1101,
		"name": "Silvia Riorda",
		"title": "Manager, Vocational Services",
		"phones": [{
			"id": 1101,
			"department": null,
			"extension": null,
			"number": "305-326-4156",
			"number_type": "voice",
			"vanity_number": null
		}]
	},
	{
		"department": null,
		"email": "sriorda@goodwillmiami.org",
		"id": 1102,
		"name": "Silvia Riorda",
		"title": "Director of Vocational Programs",
		"phones": [{
			"id": 1102,
			"department": null,
			"extension": null,
			"number": "305-326-4156",
			"number_type": "voice",
			"vanity_number": null
		}]
	},
	{
		"department": null,
		"email": "questions@goodwillsouthflorida.org",
		"id": 1103,
		"name": "Robert Randall",
		"title": "Vice President, Donated Goods",
		"phones": [{
			"id": 1103,
			"department": null,
			"extension": null,
			"number": "305-326-9114",
			"number_type": "voice",
			"vanity_number": null
		}]
	},
	{
		"department": null,
		"email": "emartinez@goodwillmiami.org",
		"id": 1104,
		"name": "Evelyn Martinez",
		"title": "Vocational Evaluation Manager",
		"phones": [{
			"id": 1104,
			"department": null,
			"extension": null,
			"number": "305-326-4166",
			"number_type": "voice",
			"vanity_number": null
		}]
	},
	{
		"department": null,
		"email": "rridgeway@goodwillmiami.org",
		"id": 1105,
		"name": "Roxana Ridgeway",
		"title": "Job Development and Placement Manager",
		"phones": [{
			"id": 1105,
			"department": null,
			"extension": null,
			"number": "305-326-4205",
			"number_type": "voice",
			"vanity_number": null
		}]
	},
	{
		"department": null,
		"email": "admissions@goodwillmiami.org",
		"id": 8115,
		"name": "Admissions Department",
		"title": null,
		"phones": [{
			"id": 8115,
			"department": null,
			"extension": null,
			"number": "305-326-4226",
			"number_type": "voice",
			"vanity_number": null
		}]
	}],
	"phones": [{
		"id": 1096,
		"department": null,
		"extension": null,
		"number": "305-325-9114",
		"number_type": "voice",
		"vanity_number": null
	},
	{
		"id": 1097,
		"department": null,
		"extension": null,
		"number": "305-325-9114",
		"number_type": "voice",
		"vanity_number": null
	},
	{
		"id": 1098,
		"department": null,
		"extension": null,
		"number": "305-325-9114",
		"number_type": "voice",
		"vanity_number": null
	},
	{
		"id": 1099,
		"department": null,
		"extension": null,
		"number": "305-326-4166",
		"number_type": "voice",
		"vanity_number": null
	},
	{
		"id": 1100,
		"department": null,
		"extension": null,
		"number": "305-326-4205",
		"number_type": "voice",
		"vanity_number": null
	},
	{
		"id": 1101,
		"department": null,
		"extension": null,
		"number": "305-326-4156",
		"number_type": "voice",
		"vanity_number": null
	},
	{
		"id": 1102,
		"department": null,
		"extension": null,
		"number": "305-326-4156",
		"number_type": "voice",
		"vanity_number": null
	},
	{
		"id": 1103,
		"department": null,
		"extension": null,
		"number": "305-326-9114",
		"number_type": "voice",
		"vanity_number": null
	},
	{
		"id": 1104,
		"department": null,
		"extension": null,
		"number": "305-326-4166",
		"number_type": "voice",
		"vanity_number": null
	},
	{
		"id": 1105,
		"department": null,
		"extension": null,
		"number": "305-326-4205",
		"number_type": "voice",
		"vanity_number": null
	},
	{
		"id": 8115,
		"department": null,
		"extension": null,
		"number": "305-326-4226",
		"number_type": "voice",
		"vanity_number": null
	}]
}