{
	"id": 5092,
	"accreditations": [],
	"alternate_name": null,
	"date_incorporated": null,
	"description": "Family Network on Disabilities is a national network of individuals of all ages who may be at-risk, have disabilities, or have special needs and their families, professionals, and concerned citizens. The mission of FND is to strive for the complete integration and equality of persons with disabilities in a society without barriers and to serve families of children with disabilities, ages birth through 26, who have the full range of disabilities. \n\n###COL###\n###MON###",
	"email": null,
	"funding_sources": [],
	"licenses": [],
	"name": "FAMILY NETWORK ON DISABILITIES, INC.",
	"website": "http://www.fndusa.org",
	"slug": "family-network-on-disabilities-inc",
	"url": "https://miamiopen211-api.herokuapp.com/api/organizations/family-network-on-disabilities-inc",
	"locations_url": "https://miamiopen211-api.herokuapp.com/api/organizations/family-network-on-disabilities-inc/locations",
	"contacts": [{
		"department": null,
		"email": "richlabelle@fndusa.org",
		"id": 5092,
		"name": "Rich La Belle",
		"title": "Executive Director",
		"phones": [{
			"id": 5092,
			"department": null,
			"extension": null,
			"number": "800-825-5736",
			"number_type": "voice",
			"vanity_number": null
		}]
	},
	{
		"department": null,
		"email": "misti@fndfl.org",
		"id": 5093,
		"name": "Misti Pollaro",
		"title": "Parent Resource Specialist",
		"phones": [{
			"id": 5093,
			"department": null,
			"extension": null,
			"number": "800-825-5736",
			"number_type": "voice",
			"vanity_number": null
		}]
	}],
	"phones": [{
		"id": 5092,
		"department": null,
		"extension": null,
		"number": "800-825-5736",
		"number_type": "voice",
		"vanity_number": null
	},
	{
		"id": 5093,
		"department": null,
		"extension": null,
		"number": "800-825-5736",
		"number_type": "voice",
		"vanity_number": null
	}]
}