{
	"id": 3350,
	"active": true,
	"admin_emails": [],
	"alternate_name": null,
	"coordinates": [-80,
	26],
	"description": "See listed services",
	"latitude": 26,
	"longitude": -80,
	"name": "Miami, FL",
	"short_desc": null,
	"slug": "miami-fl-2624-nw-21st-terrace",
	"website": null,
	"updated_at": "2017-01-09T10:15:05.860-08:00",
	"url": "https://miamiopen211-api.herokuapp.com/api/locations/miami-fl-2624-nw-21st-terrace",
	"address": {
		"id": 1651,
		"address_1": "2624 NW 21st Terrace",
		"address_2": null,
		"city": "Miami",
		"state_province": "FL",
		"postal_code": "33142"
	},
	"organization": {
		"id": 3350,
		"accreditations": [],
		"alternate_name": null,
		"date_incorporated": null,
		"description": "Provides new clothing, shoes, etc. free of charge to abused, neglected and homeless children in shelters and foster care, ages 0-18 years old.",
		"email": null,
		"funding_sources": [],
		"licenses": [],
		"name": "NEAT STUFF, INC.",
		"website": "http://www.neatstuffhelpkids.org",
		"slug": "neat-stuff-inc",
		"url": "https://miamiopen211-api.herokuapp.com/api/organizations/neat-stuff-inc",
		"locations_url": "https://miamiopen211-api.herokuapp.com/api/organizations/neat-stuff-inc/locations"
	},
	"phones": [{
		"id": 3350,
		"department": null,
		"extension": "1.0",
		"number": "305-638-5878",
		"number_type": "voice",
		"vanity_number": null
	}]
}