{
	"id": 7240,
	"active": true,
	"admin_emails": [],
	"alternate_name": null,
	"coordinates": [-80.374937,
	25.6861356],
	"description": "See listed services",
	"latitude": 25.6861356,
	"longitude": -80.374937,
	"name": "Miami, FL",
	"short_desc": null,
	"slug": "miami-fl-11050-north-kendall-drive",
	"website": null,
	"updated_at": "2017-01-09T10:15:05.860-08:00",
	"url": "https:\/\/miamiopen211-api.herokuapp.com\/api\/locations\/miami-fl-11050-north-kendall-drive",
	"address": {
		"id": 3259,
		"address_1": "11050 North Kendall Drive",
		"address_2": "Suite 102",
		"city": "Miami",
		"state_province": "FL",
		"postal_code": "33176"
	},
	"organization": {
		"id": 7240,
		"accreditations": [],
		"alternate_name": "LWTG",
		"date_incorporated": null,
		"description": "Live Well Therapy Group (LWTG) is a counseling practice with extensive experience working with children, adolescents, adults, families and couples. Some of the issues we work with are: depression, anxiety, ADD\/ADHD, grief and loss, women's issues, substance abuse, domestic violence, victims of abuse (all types), adolescent issues, eating disorders, communication skills, social skills, bipolar, and adoption issues.",
		"email": null,
		"funding_sources": [],
		"licenses": [],
		"name": "LIVE WELL THERAPY GROUP, LLC.",
		"website": "http:\/\/www.livewelltherapygroup.com",
		"slug": "live-well-therapy-group-llc",
		"url": "https:\/\/miamiopen211-api.herokuapp.com\/api\/organizations\/live-well-therapy-group-llc",
		"locations_url": "https:\/\/miamiopen211-api.herokuapp.com\/api\/organizations\/live-well-therapy-group-llc\/locations"
	},
	"phones": [{
		"id": 7240,
		"department": null,
		"extension": null,
		"number": "786-332-4478",
		"number_type": "voice",
		"vanity_number": null
	}]
}