{
	"id": 7705,
	"active": true,
	"admin_emails": [],
	"alternate_name": null,
	"coordinates": [-80.3880389,
	25.7684676],
	"description": "See listed services",
	"latitude": 25.7684676,
	"longitude": -80.3880389,
	"name": "Miami, FL",
	"short_desc": null,
	"slug": "miami-fl-11800-nw-2nd-street",
	"website": null,
	"updated_at": "2017-01-09T10:15:05.860-08:00",
	"url": "https://miamiopen211-api.herokuapp.com/api/locations/miami-fl-11800-nw-2nd-street",
	"address": {
		"id": 3651,
		"address_1": "11800 NW 2nd Street",
		"address_2": null,
		"city": "Miami",
		"state_province": "FL",
		"postal_code": "33182"
	},
	"organization": {
		"id": 3437,
		"accreditations": [],
		"alternate_name": "RTG",
		"date_incorporated": null,
		"description": "The after-school program focuses on the performing arts, offering classes in dance, drama and voice. These are provided through an educational format of teacher/student classroom environments culminating in on-stage productions.",
		"email": null,
		"funding_sources": [],
		"licenses": [],
		"name": "THE ROXY THEATRE GROUP - AFTER SCHOOL PROGRAM",
		"website": "http://www.RoxyPAC.com",
		"slug": "the-roxy-theatre-group-after-school-program",
		"url": "https://miamiopen211-api.herokuapp.com/api/organizations/the-roxy-theatre-group-after-school-program",
		"locations_url": "https://miamiopen211-api.herokuapp.com/api/organizations/the-roxy-theatre-group-after-school-program/locations"
	},
	"phones": [{
		"id": 7705,
		"department": null,
		"extension": null,
		"number": "305-226-0030",
		"number_type": "voice",
		"vanity_number": null
	}]
}