{
	"id": 5120,
	"active": true,
	"admin_emails": [],
	"alternate_name": null,
	"coordinates": [-80,
	26],
	"description": "See listed services",
	"latitude": 26,
	"longitude": -80,
	"name": "Fort Lauderdale, FL",
	"short_desc": null,
	"slug": "fort-lauderdale-fl-67c2e2c1-24d3-453a-9eb1-7c75a3292dc7",
	"website": null,
	"updated_at": "2017-01-09T10:15:05.860-08:00",
	"url": "https://miamiopen211-api.herokuapp.com/api/locations/fort-lauderdale-fl-67c2e2c1-24d3-453a-9eb1-7c75a3292dc7",
	"address": {
		"id": 2164,
		"address_1": "2700 West Oakland Park Boulevard",
		"address_2": "Suite 21",
		"city": "Fort Lauderdale",
		"state_province": "FL",
		"postal_code": "33311"
	},
	"organization": {
		"id": 5119,
		"accreditations": [],
		"alternate_name": null,
		"date_incorporated": null,
		"description": "Empowers women and men to become self-sufficient by providing assistance with health & wellness, education, safety, prevention, and job training; provides life skills management, career development seminars, image consulting, appropriate attire for interviews, outreach seminars/workshops, individual and group counseling.",
		"email": null,
		"funding_sources": [],
		"licenses": [],
		"name": "POSITIVE IMAGES ENTERPRISES, INC.",
		"website": "http://www.positiveimagesflorida.com",
		"slug": "positive-images-enterprises-inc",
		"url": "https://miamiopen211-api.herokuapp.com/api/organizations/positive-images-enterprises-inc",
		"locations_url": "https://miamiopen211-api.herokuapp.com/api/organizations/positive-images-enterprises-inc/locations"
	},
	"phones": [{
		"id": 5120,
		"department": null,
		"extension": null,
		"number": "954-484-1824",
		"number_type": "voice",
		"vanity_number": null
	}]
}