{
	"id": 628,
	"accreditations": [],
	"alternate_name": null,
	"date_incorporated": null,
	"description": "Le Jardin Community Center, Inc. is a nonprofit agency founded in 1986. Le Jardin has over 28 years of experience in providing childcare services to the southern regions of Miami-Dade County. When the agency began, we only served 20 children, currently we serve over 600 children annually from birth to five years of age. In addition to providing exceptional care to the children, we provide comprehensive services to the parents, such as case management, parental training, health services, and nutritional training. Our family workers assist the families by making referrals to educational, vocational, employment, housing, medical, dental and transportation providers. Le Jardin Community Center, Inc. also provides supplemental services to promote and support family and child health, and special education services to children with IEP/IFSPGu00c7u00d6s.",
	"email": null,
	"funding_sources": [],
	"licenses": [],
	"name": "LE JARDIN COMMUNITY CENTER, INC.",
	"website": "http://www.lejardinccinc.org/",
	"slug": "le-jardin-community-center-inc",
	"url": "https://miamiopen211-api.herokuapp.com/api/organizations/le-jardin-community-center-inc",
	"locations_url": "https://miamiopen211-api.herokuapp.com/api/organizations/le-jardin-community-center-inc/locations",
	"contacts": [{
		"department": null,
		"email": "administrator@lejardinccinc.org",
		"id": 628,
		"name": "Eduardo Berrones",
		"title": "Executive Director",
		"phones": [{
			"id": 628,
			"department": null,
			"extension": null,
			"number": "305-245-7299",
			"number_type": "voice",
			"vanity_number": null
		}]
	},
	{
		"department": null,
		"email": "administrator@lejardinccinc.org",
		"id": 630,
		"name": "Maria Motta",
		"title": "Curriculum Specialist",
		"phones": [{
			"id": 630,
			"department": null,
			"extension": null,
			"number": "305-245-2422",
			"number_type": "voice",
			"vanity_number": null
		}]
	},
	{
		"department": null,
		"email": "administrator@lejardinccinc.org",
		"id": 631,
		"name": "Monica Mills",
		"title": "Curriculum Specialist",
		"phones": [{
			"id": 631,
			"department": null,
			"extension": null,
			"number": "305-248-3633",
			"number_type": "voice",
			"vanity_number": null
		}]
	},
	{
		"department": null,
		"email": "administrator@lejardinccinc.org",
		"id": 632,
		"name": "Zuly Navarrete",
		"title": "Curriculum Specialist",
		"phones": [{
			"id": 632,
			"department": null,
			"extension": null,
			"number": "305-245-5797",
			"number_type": "voice",
			"vanity_number": null
		}]
	},
	{
		"department": null,
		"email": "administrator@lejardinccinc.org",
		"id": 633,
		"name": "Zuly Navarrete",
		"title": "Curriculum Specialist",
		"phones": [{
			"id": 633,
			"department": null,
			"extension": null,
			"number": "305-245-5797",
			"number_type": "voice",
			"vanity_number": null
		}]
	},
	{
		"department": null,
		"email": "administrator@lejardinccinc.org",
		"id": 8094,
		"name": "Zuly Navarrete",
		"title": "Curriculum Specialist",
		"phones": [{
			"id": 8094,
			"department": null,
			"extension": null,
			"number": "305-245-7384",
			"number_type": "voice",
			"vanity_number": null
		}]
	}],
	"phones": [{
		"id": 628,
		"department": null,
		"extension": null,
		"number": "305-245-7299",
		"number_type": "voice",
		"vanity_number": null
	},
	{
		"id": 630,
		"department": null,
		"extension": null,
		"number": "305-245-2422",
		"number_type": "voice",
		"vanity_number": null
	},
	{
		"id": 631,
		"department": null,
		"extension": null,
		"number": "305-248-3633",
		"number_type": "voice",
		"vanity_number": null
	},
	{
		"id": 632,
		"department": null,
		"extension": null,
		"number": "305-245-5797",
		"number_type": "voice",
		"vanity_number": null
	},
	{
		"id": 633,
		"department": null,
		"extension": null,
		"number": "305-245-5797",
		"number_type": "voice",
		"vanity_number": null
	},
	{
		"id": 8094,
		"department": null,
		"extension": null,
		"number": "305-245-7384",
		"number_type": "voice",
		"vanity_number": null
	}]
}