{
	"id": 7457,
	"active": true,
	"admin_emails": [],
	"alternate_name": null,
	"coordinates": [-80.366913,
	25.623012],
	"description": "See listed services",
	"latitude": 25.623012,
	"longitude": -80.366913,
	"name": "Miami, FL",
	"short_desc": null,
	"slug": "miami-fl-4e4911fc-b720-4609-8f9e-46184649362a",
	"website": null,
	"updated_at": "2017-01-09T10:15:05.860-08:00",
	"url": "https://miamiopen211-api.herokuapp.com/api/locations/miami-fl-4e4911fc-b720-4609-8f9e-46184649362a",
	"address": {
		"id": 3432,
		"address_1": "10750 SW 156th Terrace",
		"address_2": null,
		"city": "Miami",
		"state_province": "FL",
		"postal_code": "33170"
	},
	"organization": {
		"id": 3949,
		"accreditations": [],
		"alternate_name": null,
		"date_incorporated": null,
		"description": "Knowledge Builders of Florida, Inc. mission is to develop and implement high-quality, innovative programming and services that are outcome-focused, cost-effective, and specifically designed to improve the quality of life for underprivileged youth and their families within the communities we serve.",
		"email": null,
		"funding_sources": [],
		"licenses": [],
		"name": "KNOWLEDGE BUILDERS OF FLORIDA, INC.",
		"website": "http://kb-florida.org",
		"slug": "knowledge-builders-of-florida-inc",
		"url": "https://miamiopen211-api.herokuapp.com/api/organizations/knowledge-builders-of-florida-inc",
		"locations_url": "https://miamiopen211-api.herokuapp.com/api/organizations/knowledge-builders-of-florida-inc/locations"
	},
	"phones": [{
		"id": 7457,
		"department": null,
		"extension": null,
		"number": "305-234-1645",
		"number_type": "voice",
		"vanity_number": null
	}]
}