{
	"id": 6194,
	"active": true,
	"admin_emails": [],
	"alternate_name": null,
	"coordinates": [-80,
	26],
	"description": "See listed services",
	"latitude": 26,
	"longitude": -80,
	"name": "Miami, FL",
	"short_desc": null,
	"slug": "miami-fl-13550-memorial-highway",
	"website": null,
	"updated_at": "2017-01-09T10:15:05.860-08:00",
	"url": "https:\/\/miamiopen211-api.herokuapp.com\/api\/locations\/miami-fl-13550-memorial-highway",
	"address": {
		"id": 2634,
		"address_1": "13550 Memorial Highway",
		"address_2": null,
		"city": "Miami",
		"state_province": "FL",
		"postal_code": "33161"
	},
	"organization": {
		"id": 6194,
		"accreditations": [],
		"alternate_name": null,
		"date_incorporated": null,
		"description": "Summer House provides in-patient substance abuse detox and treatment. Helps with alcohol detox, and detox from: Heroin, Methadone, Oxy-Contin, Suboxone, Benzodiazepine, Xanax, Valium, and Cocaine. Summer House is an in-patient substance abuse center. Our mission is to make the detoxification process comfortable by giving the person a strong liquid narcotic cocktail in reducing doses every four hours during your stay in a controlled environment until they are clean.",
		"email": null,
		"funding_sources": [],
		"licenses": [],
		"name": "SUMMER HOUSE DETOX CENTER, LLC.",
		"website": "http:\/\/www.summerhousedetoxcenter.com\/",
		"slug": "summer-house-detox-center-llc",
		"url": "https:\/\/miamiopen211-api.herokuapp.com\/api\/organizations\/summer-house-detox-center-llc",
		"locations_url": "https:\/\/miamiopen211-api.herokuapp.com\/api\/organizations\/summer-house-detox-center-llc\/locations"
	},
	"phones": [{
		"id": 6194,
		"department": null,
		"extension": null,
		"number": "305-892-8440",
		"number_type": "voice",
		"vanity_number": null
	}]
}