[
  {
    "id": 1,
    "active": true,
    "admin_emails": [
      "admin@example.com"
    ],
    "alternate_name": "",
    "coordinates": [],
    "description": "This is the description of the location.",
    "latitude": null,
    "longitude": null,
    "name": "Location One",
    "short_desc": null,
    "slug": "location-one",
    "website": null,
    "updated_at": "2016-06-14T16:02:45.812-07:00",
    "url": "https://example.com",
    "address": null,
    "organization": {
      "id": 1,
      "accreditations": [],
      "alternate_name": "An Alternate name",
      "date_incorporated": null,
      "description": "This is a description of the organization, providing details about what it does.",
      "email": "info@example.com",
      "funding_sources": [],
      "licenses": [],
      "name": "First Organization",
      "website": "https://example.com",
      "slug": "first-organization",
      "url": "https://example.org",
      "locations_url": "https://example.com"
    },
    "phones": []
  },
  {
    "id": 2,
    "active": true,
    "admin_emails": [
      "admin@example.com"
    ],
    "alternate_name": "",
    "coordinates": [],
    "description": "This is the description of the location.",
    "latitude": null,
    "longitude": null,
    "name": "Location Two",
    "short_desc": null,
    "slug": "location-two",
    "website": null,
    "updated_at": "2016-06-14T16:02:45.812-07:00",
    "url": "https://example.com",
    "address": null,
    "organization": {
      "id": 1,
      "accreditations": [],
      "alternate_name": "An Alternate name",
      "date_incorporated": null,
      "description": "This is a description of the organization, providing details about what it does.",
      "email": "info@example.com",
      "funding_sources": [],
      "licenses": [],
      "name": "Second Organization",
      "website": "https://example.com",
      "slug": "second-organization",
      "url": "https://example.org",
      "locations_url": "https://example.com"
    },
    "phones": []
  },
  {
    "id": 3,
    "active": true,
    "admin_emails": [
      "admin@example.com"
    ],
    "alternate_name": "",
    "coordinates": [],
    "description": "This is the description of the location.",
    "latitude": null,
    "longitude": null,
    "name": "Location Three",
    "short_desc": null,
    "slug": "location-three",
    "website": null,
    "updated_at": "2016-06-14T16:02:45.812-07:00",
    "url": "https://example.com",
    "address": null,
    "organization": {
      "id": 3,
      "accreditations": [],
      "alternate_name": "An Alternate name",
      "date_incorporated": null,
      "description": "This is a description of the organization, providing details about what it does.",
      "email": "info@example.com",
      "funding_sources": [],
      "licenses": [],
      "name": "Third Organization",
      "website": "https://example.com",
      "slug": "third-organization",
      "url": "https://example.org",
      "locations_url": "https://example.com"
    },
    "phones": []
  }
]
