{
	"id": 7434,
	"accreditations": [],
	"alternate_name": null,
	"date_incorporated": null,
	"description": "The Family Planning program offers many services, including information on baby spacing, abstinence, avoiding sexually transmitted diseases or infections (STDs or STIs) and birth control methods. There are clinics conveniently located throughout Miami-Dade County.",
	"email": null,
	"funding_sources": [],
	"licenses": [],
	"name": "FL DOH M-DC - FAMILY PLANNING",
	"website": "http://miamidade.floridahealth.gov/programs-and-services/clinical-and-nutrition-services/womens-health/women_family%20planning/index.html",
	"slug": "fl-doh-m-dc-family-planning",
	"url": "https://miamiopen211-api.herokuapp.com/api/organizations/fl-doh-m-dc-family-planning",
	"locations_url": "https://miamiopen211-api.herokuapp.com/api/organizations/fl-doh-m-dc-family-planning/locations",
	"contacts": [{
		"department": null,
		"email": "lillian_rivera@flhealth.gov",
		"id": 7435,
		"name": "Lillian Rivera, RN, MSN, PhD",
		"title": "Administrator",
		"phones": [{
			"id": 7435,
			"department": null,
			"extension": null,
			"number": "786-336-1437",
			"number_type": "voice",
			"vanity_number": null
		}]
	},
	{
		"department": null,
		"email": "lillian_rivera@flhealth.gov",
		"id": 7437,
		"name": "Lillian Rivera, RN, MSN, PhD",
		"title": "Administrator",
		"phones": [{
			"id": 7437,
			"department": null,
			"extension": null,
			"number": "786-336-1437",
			"number_type": "voice",
			"vanity_number": null
		}]
	},
	{
		"department": null,
		"email": "lillian_rivera@flhealth.gov",
		"id": 7438,
		"name": "Lillian Rivera, RN, MSN, PhD",
		"title": "Administrator",
		"phones": [{
			"id": 7438,
			"department": null,
			"extension": null,
			"number": "786-336-1437",
			"number_type": "voice",
			"vanity_number": null
		}]
	},
	{
		"department": null,
		"email": "lillian_rivera@flhealth.gov",
		"id": 7439,
		"name": "Lillian Rivera, RN, MSN, PhD",
		"title": "Administrator",
		"phones": [{
			"id": 7439,
			"department": null,
			"extension": null,
			"number": "786-336-1437",
			"number_type": "voice",
			"vanity_number": null
		}]
	}],
	"phones": [{
		"id": 7435,
		"department": null,
		"extension": null,
		"number": "786-336-1437",
		"number_type": "voice",
		"vanity_number": null
	},
	{
		"id": 7437,
		"department": null,
		"extension": null,
		"number": "786-336-1437",
		"number_type": "voice",
		"vanity_number": null
	},
	{
		"id": 7438,
		"department": null,
		"extension": null,
		"number": "786-336-1437",
		"number_type": "voice",
		"vanity_number": null
	},
	{
		"id": 7439,
		"department": null,
		"extension": null,
		"number": "786-336-1437",
		"number_type": "voice",
		"vanity_number": null
	}]
}